odoo/addons/product_variant_specific_description/README.rst
odoo/addons/product_variant_specific_description/__init__.py
odoo/addons/product_variant_specific_description/__manifest__.py
odoo/addons/product_variant_specific_description/init_hook.py
odoo/addons/product_variant_specific_description/i18n/es.po
odoo/addons/product_variant_specific_description/i18n/it.po
odoo/addons/product_variant_specific_description/i18n/product_variant_specific_description.pot
odoo/addons/product_variant_specific_description/models/__init__.py
odoo/addons/product_variant_specific_description/models/product_product.py
odoo/addons/product_variant_specific_description/models/product_template.py
odoo/addons/product_variant_specific_description/readme/CONTRIBUTORS.rst
odoo/addons/product_variant_specific_description/readme/DESCRIPTION.rst
odoo/addons/product_variant_specific_description/static/description/icon.png
odoo/addons/product_variant_specific_description/static/description/index.html
odoo/addons/product_variant_specific_description/tests/__init__.py
odoo/addons/product_variant_specific_description/tests/test_product_variant_description.py
odoo/addons/product_variant_specific_description/views/product_template_view.xml
odoo/addons/product_variant_specific_description/views/product_view.xml
odoo_addon_product_variant_specific_description-16.0.1.0.1.4.dist-info/METADATA
odoo_addon_product_variant_specific_description-16.0.1.0.1.4.dist-info/WHEEL
odoo_addon_product_variant_specific_description-16.0.1.0.1.4.dist-info/top_level.txt
odoo_addon_product_variant_specific_description-16.0.1.0.1.4.dist-info/RECORD
